encryptpy/__init__.py
encryptpy/__main__.py
encryptpy/cli.py
encryptpy/compiler.py
encryptpy/config.py
encryptpy/utils.py
encryptpy-1.0.6.dist-info/licenses/LICENSE
examples/package_a/__init__.py
examples/package_a/main.py
examples/package_a/setup.py
examples/package_a/utils.py
encryptpy-1.0.6.dist-info/METADATA
encryptpy-1.0.6.dist-info/WHEEL
encryptpy-1.0.6.dist-info/entry_points.txt
encryptpy-1.0.6.dist-info/top_level.txt
encryptpy-1.0.6.dist-info/RECORD
