Metadata-Version: 2.4
Name: encryptpy
Version: 1.0.6
Summary: Use Cython to compile Python code to binary and support git-diff to get changed files conveniently.
Author-email: Amchii <finethankuandyou@gmail.com>
License-Expression: MIT
Project-URL: Homepage, https://github.com/amchii/encryptpy
Project-URL: Repository, https://github.com/amchii/encryptpy
Classifier: Intended Audience :: Developers
Classifier: Programming Language :: Python :: 3 :: Only
Classifier: Operating System :: OS Independent
Classifier: Topic :: Software Development :: Compilers
License-File: LICENSE
Requires-Dist: cython
Requires-Dist: click
Requires-Dist: gitpython
Dynamic: license-file
